__init__.py
pyCFG.py
pythonCFG-1.2.4.dist-info/LICENSE
pythonCFG-1.2.4.dist-info/METADATA
pythonCFG-1.2.4.dist-info/WHEEL
pythonCFG-1.2.4.dist-info/top_level.txt
pythonCFG-1.2.4.dist-info/RECORD
