Metadata-Version: 2.1
Name: pythonCFG
Version: 1.2.4
Summary: An easy-to-use library for implementing and visualizing a control flow graph in python. 
Author-email: Calastrophe <vmxoperation@proton.me>
Project-URL: Homepage, https://github.com/Calastrophe/pythonCFG
Project-URL: Bug Tracker, https://github.com/Calastrophe/pythonCFG/issues
Classifier: Programming Language :: Python :: 3.10
Classifier: License :: OSI Approved :: GNU General Public License v3 (GPLv3)
Classifier: Operating System :: OS Independent
Requires-Python: >=3.10
License-File: LICENSE
